swagflask/__init__.py
swagflask/swagger.py
swagflask-0.2.0.dist-info/licenses/LICENSE
swagflask-0.2.0.dist-info/METADATA
swagflask-0.2.0.dist-info/WHEEL
swagflask-0.2.0.dist-info/top_level.txt
swagflask-0.2.0.dist-info/RECORD
