Metadata-Version: 2.4
Name: swagflask
Version: 0.2.0
Summary: Swagger UI for Flask - Automatically configure Swagger UI for Flask applications, just like FastAPI's /docs endpoint
Home-page: https://github.com/rithwiksb/swagflask
Author: Rithwik
Author-email: Rithwik <rithwiksbharadwaj@gmail.com>
License: MIT
Project-URL: Homepage, https://github.com/rithwiksb/swagflask
Project-URL: Documentation, https://github.com/rithwiksb/swagflask#readme
Project-URL: Repository, https://github.com/rithwiksb/swagflask
Project-URL: Bug Tracker, https://github.com/rithwiksb/swagflask/issues
Keywords: flask,swagger,openapi,api,documentation,rest
Classifier: Development Status :: 4 - Beta
Classifier: Intended Audience :: Developers
Classifier: License :: OSI Approved :: MIT License
Classifier: Programming Language :: Python :: 3
Classifier: Programming Language :: Python :: 3.7
Classifier: Programming Language :: Python :: 3.8
Classifier: Programming Language :: Python :: 3.9
Classifier: Programming Language :: Python :: 3.10
Classifier: Programming Language :: Python :: 3.11
Classifier: Programming Language :: Python :: 3.12
Classifier: Framework :: Flask
Classifier: Topic :: Software Development :: Libraries :: Python Modules
Classifier: Topic :: Documentation
Requires-Python: >=3.7
License-File: LICENSE
Requires-Dist: Flask>=2.0.0
Provides-Extra: dev
Requires-Dist: pytest>=7.0.0; extra == "dev"
Requires-Dist: pytest-flask>=1.2.0; extra == "dev"
Requires-Dist: black>=22.0.0; extra == "dev"
Requires-Dist: flake8>=4.0.0; extra == "dev"
Dynamic: author
Dynamic: home-page
Dynamic: license-file
Dynamic: requires-python
